steer/__init__.py
steer/cli.py
steer/config.py
steer/core.py
steer/exporter.py
steer/llm.py
steer/mock.py
steer/schemas.py
steer/server.py
steer/storage.py
steer/ui/404.html
steer/ui/__next.__PAGE__.txt
steer/ui/__next._full.txt
steer/ui/__next._head.txt
steer/ui/__next._index.txt
steer/ui/__next._tree.txt
steer/ui/_next/static/chunks/0d03996d4dc2f4a9.js
steer/ui/_next/static/chunks/42879de7b8087bc9.js
steer/ui/_next/static/chunks/6d94cd2de0f5bc76.js
steer/ui/_next/static/chunks/752bea8c8f15cedd.js
steer/ui/_next/static/chunks/85e2cd8235bb75d4.css
steer/ui/_next/static/chunks/940e70d544422cd1.js
steer/ui/_next/static/chunks/a6dad97d9634a72d.js
steer/ui/_next/static/chunks/d217698e32abd0dc.js
steer/ui/_next/static/chunks/turbopack-0d14a708cd8eabb2.js
steer/ui/_next/static/cxvsdwfl0GLod-qFpT8EQ/_buildManifest.js
steer/ui/_next/static/cxvsdwfl0GLod-qFpT8EQ/_clientMiddlewareManifest.json
steer/ui/_next/static/cxvsdwfl0GLod-qFpT8EQ/_ssgManifest.js
steer/ui/_next/static/media/1bffadaabf893a1e-s.7cd81963.woff2
steer/ui/_next/static/media/2bbe8d2671613f1f-s.76dcb0b2.woff2
steer/ui/_next/static/media/2c55a0e60120577a-s.2a48534a.woff2
steer/ui/_next/static/media/5476f68d60460930-s.c995e352.woff2
steer/ui/_next/static/media/83afe278b6a6bb3c-s.p.3a6ba036.woff2
steer/ui/_next/static/media/9c72aa0f40e4eef8-s.18a48cbc.woff2
steer/ui/_next/static/media/ad66f9afd8947f86-s.7a40eb73.woff2
steer/ui/_next/static/media/favicon.0b3bf435.ico
steer/ui/_not-found/__next._full.txt
steer/ui/_not-found/__next._head.txt
steer/ui/_not-found/__next._index.txt
steer/ui/_not-found/__next._not-found.__PAGE__.txt
steer/ui/_not-found/__next._not-found.txt
steer/ui/_not-found/__next._tree.txt
steer/ui/_not-found.html
steer/ui/_not-found.txt
steer/ui/favicon.ico
steer/ui/file.svg
steer/ui/globe.svg
steer/ui/index.html
steer/ui/index.txt
steer/ui/next.svg
steer/ui/vercel.svg
steer/ui/window.svg
steer/utils.py
steer/verifiers.py
steer/worker.py
steer_sdk-0.2.4.dist-info/METADATA
steer_sdk-0.2.4.dist-info/WHEEL
steer_sdk-0.2.4.dist-info/entry_points.txt
steer_sdk-0.2.4.dist-info/RECORD
