Metadata-Version: 2.4
Name: steer-sdk
Version: 0.2.4
Summary: The Active Reliability Layer for AI Agents
Author: Steer Dev
Author-email: hello@steer-labs.com
Requires-Python: >=3.13,<4.0
Classifier: Programming Language :: Python :: 3
Classifier: Programming Language :: Python :: 3.13
Classifier: Programming Language :: Python :: 3.14
Requires-Dist: fastapi (>=0.122.0,<0.123.0)
Requires-Dist: google (>=3.0.0,<4.0.0)
Requires-Dist: google-cloud-storage (>=3.6.0,<4.0.0)
Requires-Dist: httpx (>=0.28.1,<0.29.0)
Requires-Dist: langchain (>=1.1.0,<2.0.0)
Requires-Dist: langchain-openai (>=1.1.0,<2.0.0)
Requires-Dist: litellm (>=1.80.5,<2.0.0)
Requires-Dist: opentelemetry-api (>=1.38.0,<2.0.0)
Requires-Dist: pydantic (>=2.12.4,<3.0.0)
Requires-Dist: python-dotenv (>=1.2.1,<2.0.0)
Requires-Dist: pyyaml (>=6.0.3,<7.0.0)
Requires-Dist: rich (>=14.2.0,<15.0.0)
Requires-Dist: uvicorn (>=0.38.0,<0.39.0)
Project-URL: Bug Tracker, https://github.com/imtt-dev/steer/issues
Project-URL: Homepage, https://steer-labs.com
Project-URL: Repository, https://github.com/imtt-dev/steer
